cli/__init__.py
cli/cli.py
easytainer_cli-0.0.6.dist-info/DESCRIPTION.rst
easytainer_cli-0.0.6.dist-info/METADATA
easytainer_cli-0.0.6.dist-info/RECORD
easytainer_cli-0.0.6.dist-info/WHEEL
easytainer_cli-0.0.6.dist-info/entry_points.txt
easytainer_cli-0.0.6.dist-info/metadata.json
easytainer_cli-0.0.6.dist-info/top_level.txt
