Metadata-Version: 2.0
Name: easytainer-cli
Version: 0.0.6
Summary: Command line interface for easytainer.cloud
Home-page: https://gitlab.com/kai.richard.koenig/easytainer-cli
Author: Kai Richard Koenig
Author-email: kai.richard.koenig@gmail.com
License: BSD3
Platform: UNKNOWN
Classifier: License :: OSI Approved :: MIT License
Classifier: Programming Language :: Python
Classifier: Programming Language :: Python :: 2.7
Classifier: Programming Language :: Python :: 3
Classifier: Programming Language :: Python :: 3.3
Classifier: Programming Language :: Python :: 3.4
Classifier: Programming Language :: Python :: 3.5
Classifier: Programming Language :: Python :: 3.6
Classifier: Programming Language :: Python :: Implementation :: CPython
Requires-Dist: requests
Requires-Dist: click
